lido/__init__.py
lido/beacon.py
lido/constants/chains.py
lido/constants/contract_addresses.py
lido/constants/withdrawal_credentials.py
lido/contracts/abi/goerli/Lido.json
lido/contracts/abi/goerli/NodeOperatorsRegistry.json
lido/contracts/abi/mainnet/Lido.json
lido/contracts/abi/mainnet/NodeOperatorsRegistry.json
lido/contracts/abi/ropsten/Lido.json
lido/contracts/abi/ropsten/NodeOperatorsRegistry.json
lido/contracts/abi_loader.py
lido/contracts/w3_contracts.py
lido/eth2deposit/README.md
lido/eth2deposit/settings.py
lido/eth2deposit/utils/constants.py
lido/eth2deposit/utils/ssz.py
lido/find_duplicates.py
lido/get_operators_data.py
lido/get_operators_keys.py
lido/get_stats.py
lido/main.py
lido/multicall/README.md
lido/multicall/__init__.py
lido/multicall/call.py
lido/multicall/constants.py
lido/multicall/multicall.py
lido/multicall/signature.py
lido/utils/data_actuality.py
lido/validate_keys.py
lido-1.1.0.dist-info/LICENSE
lido-1.1.0.dist-info/WHEEL
lido-1.1.0.dist-info/METADATA
lido-1.1.0.dist-info/RECORD
