Metadata-Version: 2.1
Name: lido
Version: 1.1.0
Summary: Network helpers for Lido
Home-page: https://lido.fi
License: MIT
Author: Lido
Author-email: info@lido.fi
Requires-Python: >3.7.1,<4
Classifier: License :: OSI Approved :: MIT License
Classifier: Programming Language :: Python :: 3
Classifier: Programming Language :: Python :: 3.8
Classifier: Programming Language :: Python :: 3.9
Requires-Dist: py-ecc (>=5.1.0,<6.0.0)
Requires-Dist: requests (>=2.25.1,<3.0.0)
Requires-Dist: ssz (>=0.2.4,<0.3.0)
Requires-Dist: web3 (>=5.15.0,<6.0.0)
Project-URL: Repository, https://github.com/lidofinance/lido-python
